datacenter_du/__init__.py
datacenter_du/downloader.py
datacenter_du/transfer.py
datacenter_du/uploader.py
datacenter_du-0.1.4.dist-info/AUTHORS.rst
datacenter_du-0.1.4.dist-info/METADATA
datacenter_du-0.1.4.dist-info/WHEEL
datacenter_du-0.1.4.dist-info/top_level.txt
datacenter_du-0.1.4.dist-info/RECORD
