Metadata-Version: 2.1
Name: datacenter-du
Version: 0.1.4
Summary: Datacenter Downloader & Uploader
Home-page: https://github.com/taceywong/datacenter_du
Author: Datacenter Downloader & Uploader
Author-email: xinyong.wang@xtalpi.com
License: UNKNOWN
Keywords: datacenter_du
Platform: UNKNOWN
Classifier: Development Status :: 2 - Pre-Alpha
Classifier: Intended Audience :: Developers
Classifier: Natural Language :: English
Classifier: Programming Language :: Python :: 3
Classifier: Programming Language :: Python :: 3.5
Classifier: Programming Language :: Python :: 3.6
Classifier: Programming Language :: Python :: 3.7
Classifier: Programming Language :: Python :: 3.8
Requires-Python: >=3.5
Requires-Dist: requests
